__init__.py
query.py
setup.py
tide_query.py
tide_query.egg-info/PKG-INFO
tide_query.egg-info/SOURCES.txt
tide_query.egg-info/dependency_links.txt
tide_query.egg-info/requires.txt
tide_query.egg-info/top_level.txt