Metadata-Version: 1.0
Name: tide-query
Version: 0.0.1
Summary: This is a spider helper.
Home-page: UNKNOWN
Author: Jover Zhang
Author-email: joverzh@gmail.com
License: UNKNOWN
Platform: UNKNOWN
